{
"full_datetime": "", 
"full_date": "Sat 15 Sep 04:20:36 UTC 2018", 
"datetime": "2018-09-15 04:20:36", 
"timestamp": "20180915042036", 
"daymonthyear": "Saturday 15 September 2018", 
"YYYY": "2018", 
"MM": "09", 
"DD": "15", 
"julian_day": "", 
"update_window": "0000-0559", 
"update_number": "", 
"update_frequency": "15", 
"update_at": "04:20", 
"update_timestamp": "04:35", 
"update_window_start": "01:30", 
"update_window_stop": "04:29", 
"tournament": {
  "tournament_year": "2018", 
  "tournament_week": "37", 
  "tournament_day": "1", 
  "tournament_day_yyyy": "2018", 
  "tournament_day_mm": "09", 
  "tournament_day_dd": "14", 
  "hour_filename": "/home/ldenken/gw2/realm_avenger/tables/2018-09-14-T37-d1-hour-table", 
  "day_listing_title": "T37-d1 Fri 14 Sep 18:00:00 UTC 2018 to Sat 15 Sep 17:59:59 UTC 2018", 
  "day_post_title": "Tournament 37, Day 1", 
  "day_post_subtitle": "Fri 14 Sep 18:00:00 UTC 2018 to Sat 15 Sep 17:59:59 UTC 2018", 
  "day_filename": "T37-d1", 
  "day_results_table_url": "/tournaments/2018/09/14/T37-d1.html", 
  "week_listing_title": "Tournament 37", 
  "week_post_title": "Tournament 37", 
  "week_post_subtitle": "Fri 14 Sep 18:00:00 UTC 2018 to Fri 21 Sep 17:59:59 UTC 2018", 
  "week_filename": "/home/ldenken/gw2/realm_avenger/tables/T37", 
  "week_results_table_url": "/tournaments/2018/09/14/T37.html", 
  "schedule": [
    {"day": "1", "start": "Fri 14 Sep 18:00:00 UTC 2018", "stop": "Sat 15 Sep 17:59:59 UTC 2018"}, 
    {"day": "2", "start": "Sat 15 Sep 18:00:00 UTC 2018", "stop": "Sun 16 Sep 17:59:59 UTC 2018"}, 
    {"day": "3", "start": "Sun 16 Sep 18:00:00 UTC 2018", "stop": "Mon 17 Sep 17:59:59 UTC 2018"}, 
    {"day": "4", "start": "Mon 17 Sep 18:00:00 UTC 2018", "stop": "Tue 18 Sep 17:59:59 UTC 2018"}, 
    {"day": "5", "start": "Tue 18 Sep 18:00:00 UTC 2018", "stop": "Wed 19 Sep 17:59:59 UTC 2018"}, 
    {"day": "6", "start": "Wed 19 Sep 18:00:00 UTC 2018", "stop": "Thu 20 Sep 17:59:59 UTC 2018"}, 
    {"day": "7", "start": "Thu 20 Sep 18:00:00 UTC 2018", "stop": "Fri 21 Sep 17:59:59 UTC 2018"}
  ], 
},
"columns": [
  {"col": "COL1", "label": "01:30", "start": "Sat 15 Sep 01:30:00 UTC 2018", "stop": "Sat 15 Sep 01:44:59 UTC 2018", "url": "/tournaments/2018/09/15/T37-d1.html"},
  {"col": "COL2", "label": "01:45", "start": "Sat 15 Sep 01:45:00 UTC 2018", "stop": "Sat 15 Sep 01:59:59 UTC 2018", "url": "/tournaments/2018/09/15/T37-d2.html"},
  {"col": "COL3", "label": "02:00", "start": "Sat 15 Sep 02:00:00 UTC 2018", "stop": "Sat 15 Sep 02:14:59 UTC 2018", "url": "/tournaments/2018/09/15/T37-d3.html"},
  {"col": "COL4", "label": "02:15", "start": "Sat 15 Sep 02:15:00 UTC 2018", "stop": "Sat 15 Sep 02:29:59 UTC 2018", "url": "/tournaments/2018/09/15/T37-d4.html"},
  {"col": "COL5", "label": "02:30", "start": "Sat 15 Sep 02:30:00 UTC 2018", "stop": "Sat 15 Sep 02:44:59 UTC 2018", "url": "/tournaments/2018/09/15/T37-d5.html"},
  {"col": "COL6", "label": "02:45", "start": "Sat 15 Sep 02:45:00 UTC 2018", "stop": "Sat 15 Sep 02:59:59 UTC 2018", "url": "/tournaments/2018/09/15/T37-d6.html"},
  {"col": "COL7", "label": "03:00", "start": "Sat 15 Sep 03:00:00 UTC 2018", "stop": "Sat 15 Sep 03:14:59 UTC 2018", "url": "/tournaments/2018/09/15/T37-d7.html"},
  {"col": "COL8", "label": "03:15", "start": "Sat 15 Sep 03:15:00 UTC 2018", "stop": "Sat 15 Sep 03:29:59 UTC 2018", "url": "/tournaments/2018/09/15/T37-d8.html"},
  {"col": "COL9", "label": "03:30", "start": "Sat 15 Sep 03:30:00 UTC 2018", "stop": "Sat 15 Sep 03:44:59 UTC 2018", "url": "/tournaments/2018/09/15/T37-d9.html"},
  {"col": "COL10", "label": "03:45", "start": "Sat 15 Sep 03:45:00 UTC 2018", "stop": "Sat 15 Sep 03:59:59 UTC 2018", "url": "/tournaments/2018/09/15/T37-d10.html"},
  {"col": "COL11", "label": "04:00", "start": "Sat 15 Sep 04:00:00 UTC 2018", "stop": "Sat 15 Sep 04:14:59 UTC 2018", "url": "/tournaments/2018/09/15/T37-d11.html"},
  {"col": "COL12", "label": "04:15", "start": "Sat 15 Sep 04:15:00 UTC 2018", "stop": "Sat 15 Sep 04:29:59 UTC 2018", "url": "/tournaments/2018/09/15/T37-d12.html"}
], 
"entries": [
  {"pos": "1", "name": "Skritt Forager", "world": "Abaddon's Mouth", "1c": "", "1p": "", "2c": "3", "2p": "1", "3c": "", "3p": "", "4c": "", "4p": "", "5c": "", "5p": "", "6c": "2", "6p": "1", "7c": "5", "7p": "1", "8c": "", "8p": "", "9c": "", "9p": "", "10c": "4", "10p": "1", "11c": "5", "11p": "1", "12c": "", "12p": "", "total": "19"}, 
  {"pos": "2", "name": "Shiny!", "world": "Anvil Rock", "1c": "", "1p": "", "2c": "", "2p": "", "3c": "", "3p": "", "4c": "5", "4p": "1", "5c": "3", "5p": "1", "6c": "2", "6p": "1", "7c": "", "7p": "", "8c": "", "8p": "", "9c": "", "9p": "", "10c": "1", "10p": "2", "11c": "", "11p": "", "12c": "5", "12p": "1", "total": "16"}
],
"commentary": [
  {"comment": "1st place, with 19 kills in 2 hours of play is Skritt Forager from Abaddon's Mouth"},
  {"comment": "2nd place, with 16 kills in 1.5 hours of play is Shiny! from Anvil Rock"}
]
}
