{
"full_datetime": "Thursday 30 August 2018 21:00:13 UTC", 
"full_date": "Thursday 30 August 2018", 
"datetime": "Thu 30 Aug 2018 21:00:13 UTC", 
"timestamp": "20180830210013", 
"YYYY": "2018", 
"MM": "08", 
"DD": "30", 
"julian_day": "242", 
"update_window": "-", 
"update_number": "", 
"update_frequency": "5", 
"update_at": "21:00", 
"update_timestamp": "21:05", 
"window_start": "17:30", 
"window_stop": "21:30", 
"tournament": {
  "year": "2018", 
  "week": "34", 
  "day": "242", 
  "day_number": "7", 
  "day_results_table": "/tournaments/2018/08/30/results-table.html", 
  "schedule": [
    {"day": "1", "jday": "236", "start": "Fri 24 Aug 2018 18:00:00 UTC", "stop": "Sat 25 Aug 2018 17:59:59 UTC"}, 
    {"day": "2", "jday": "237", "start": "Sat 25 Aug 2018 18:00:00 UTC", "stop": "Sun 26 Aug 2018 17:59:59 UTC"}, 
    {"day": "3", "jday": "238", "start": "Sun 26 Aug 2018 18:00:00 UTC", "stop": "Mon 27 Aug 2018 17:59:59 UTC"}, 
    {"day": "4", "jday": "239", "start": "Mon 27 Aug 2018 18:00:00 UTC", "stop": "Tue 28 Aug 2018 17:59:59 UTC"}, 
    {"day": "5", "jday": "240", "start": "Tue 28 Aug 2018 18:00:00 UTC", "stop": "Wed 29 Aug 2018 17:59:59 UTC"}, 
    {"day": "6", "jday": "241", "start": "Wed 29 Aug 2018 18:00:00 UTC", "stop": "Thu 30 Aug 2018 17:59:59 UTC"}, 
    {"day": "7", "jday": "242", "start": "Thu 30 Aug 2018 18:00:00 UTC", "stop": "Fri 31 Aug 2018 17:59:59 UTC"}
  ], 
},
"columns": [
  {"col": "COL1", "label": "18:00", "start": "Thu 30 Aug 2018 17:30:00 UTC", "stop": "Thu 30 Aug 2018 18:00:00 UTC"},
  {"col": "COL2", "label": "18:30", "start": "Thu 30 Aug 2018 18:00:00 UTC", "stop": "Thu 30 Aug 2018 18:30:00 UTC"},
  {"col": "COL3", "label": "19:00", "start": "Thu 30 Aug 2018 18:30:00 UTC", "stop": "Thu 30 Aug 2018 19:00:00 UTC"},
  {"col": "COL4", "label": "19:30", "start": "Thu 30 Aug 2018 19:00:00 UTC", "stop": "Thu 30 Aug 2018 19:30:00 UTC"},
  {"col": "COL5", "label": "20:00", "start": "Thu 30 Aug 2018 19:30:00 UTC", "stop": "Thu 30 Aug 2018 20:00:00 UTC"},
  {"col": "COL6", "label": "20:30", "start": "Thu 30 Aug 2018 20:00:00 UTC", "stop": "Thu 30 Aug 2018 20:30:00 UTC"},
  {"col": "COL7", "label": "21:00", "start": "Thu 30 Aug 2018 20:30:00 UTC", "stop": "Thu 30 Aug 2018 21:00:00 UTC"},
  {"col": "COL8", "label": "21:30", "start": "Thu 30 Aug 2018 21:00:00 UTC", "stop": "Thu 30 Aug 2018 21:30:00 UTC"}
], 
"entries": [
  {"pos": "1", "name": "Fred Flintstone", "world": "Maguuma", "1c": "5", "1p": "8", "1t": "", "2c": "17", "2p": "2", "2t": "", "3c": "9", "3p": "11", "3t": "", "4c": "16", "4p": "4", "4t": "", "5c": "12", "5p": "5", "5t": "", "6c": "11", "6p": "4", "6t": "", "7c": "18", "7p": "2", "7t": "", "8c": "", "8p": "", "8t": "", "total": "88"}, 
  {"pos": "2", "name": "Kvothe", "world": "Yak's Bend", "1c": "7", "1p": "6", "1t": "", "2c": "23", "2p": "1", "2t": "", "3c": "17", "3p": "4", "3t": "", "4c": "6", "4p": "12", "4t": "", "5c": "16", "5p": "2", "5t": "", "6c": "", "6p": "", "6t": "", "7c": "14", "7p": "4", "7t": "", "8c": "", "8p": "", "8t": "", "total": "83"}, 
  {"pos": "2", "name": "Riker", "world": "Yak's Bend", "1c": "12", "1p": "2", "1t": "", "2c": "15", "2p": "3", "2t": "", "3c": "11", "3p": "9", "3t": "", "4c": "8", "4p": "10", "4t": "", "5c": "16", "5p": "2", "5t": "", "6c": "13", "6p": "3", "6t": "", "7c": "8", "7p": "10", "7t": "", "8c": "", "8p": "", "8t": "", "total": "83"}, 
  {"pos": "3", "name": "Bob the Dog", "world": "Yak's Bend", "1c": "2", "1p": "9", "1t": "", "2c": "7", "2p": "11", "2t": "", "3c": "17", "3p": "4", "3t": "", "4c": "20", "4p": "2", "4t": "", "5c": "14", "5p": "3", "5t": "", "6c": "8", "6p": "7", "6t": "", "7c": "12", "7p": "6", "7t": "", "8c": "", "8p": "", "8t": "", "total": "80"}, 
  {"pos": "4", "name": "Stitch!", "world": "Ring of Fire", "1c": "", "1p": "", "1t": "", "2c": "3", "2p": "15", "2t": "", "3c": "14", "3p": "6", "3t": "", "4c": "17", "4p": "3", "4t": "", "5c": "12", "5p": "5", "5t": "", "6c": "16", "6p": "1", "6t": "", "7c": "17", "7p": "3", "7t": "", "8c": "", "8p": "", "8t": "", "total": "79"}, 
  {"pos": "5", "name": "Barbara Gordon", "world": "Ruins of Surmia", "1c": "", "1p": "", "1t": "", "2c": "8", "2p": "10", "2t": "", "3c": "18", "3p": "3", "3t": "", "4c": "10", "4p": "8", "4t": "", "5c": "9", "5p": "8", "5t": "", "6c": "14", "6p": "2", "6t": "", "7c": "11", "7p": "7", "7t": "", "8c": "", "8p": "", "8t": "", "total": "70"}, 
  {"pos": "5", "name": "Batgirl", "world": "Ruins of Surmia", "1c": "", "1p": "", "1t": "", "2c": "7", "2p": "11", "2t": "", "3c": "11", "3p": "9", "3t": "", "4c": "15", "4p": "5", "4t": "", "5c": "9", "5p": "8", "5t": "", "6c": "14", "6p": "2", "6t": "", "7c": "14", "7p": "4", "7t": "", "8c": "", "8p": "", "8t": "", "total": "70"}, 
  {"pos": "5", "name": "Donald Duck", "world": "Kodash", "1c": "12", "1p": "2", "1t": "", "2c": "4", "2p": "14", "2t": "", "3c": "10", "3p": "10", "3t": "", "4c": "12", "4p": "7", "4t": "", "5c": "13", "5p": "4", "5t": "", "6c": "6", "6p": "9", "6t": "", "7c": "13", "7p": "5", "7t": "", "8c": "", "8p": "", "8t": "", "total": "70"}, 
  {"pos": "5", "name": "Homer", "world": "Yak's Bend", "1c": "8", "1p": "5", "1t": "", "2c": "12", "2p": "6", "2t": "", "3c": "", "3p": "", "3t": "", "4c": "14", "4p": "6", "4t": "", "5c": "6", "5p": "10", "5t": "", "6c": "11", "6p": "4", "6t": "", "7c": "19", "7p": "1", "7t": "", "8c": "", "8p": "", "8t": "", "total": "70"}, 
  {"pos": "6", "name": "Eric Cartman", "world": "Sanctum of Rall", "1c": "", "1p": "", "1t": "", "2c": "13", "2p": "5", "2t": "", "3c": "10", "3p": "10", "3t": "", "4c": "7", "4p": "11", "4t": "", "5c": "12", "5p": "5", "5t": "", "6c": "16", "6p": "1", "6t": "", "7c": "11", "7p": "7", "7t": "", "8c": "", "8p": "", "8t": "", "total": "69"}, 
  {"pos": "7", "name": "We Are Bob", "world": "Yak's Bend", "1c": "7", "1p": "6", "1t": "", "2c": "5", "2p": "13", "2t": "", "3c": "7", "3p": "13", "3t": "", "4c": "15", "4p": "5", "4t": "", "5c": "11", "5p": "6", "5t": "", "6c": "8", "6p": "7", "6t": "", "7c": "12", "7p": "6", "7t": "", "8c": "", "8p": "", "8t": "", "total": "65"}, 
  {"pos": "8", "name": "Vic Sage", "world": "Underworld", "1c": "", "1p": "", "1t": "", "2c": "6", "2p": "12", "2t": "", "3c": "13", "3p": "7", "3t": "", "4c": "15", "4p": "5", "4t": "", "5c": "10", "5p": "7", "5t": "", "6c": "9", "6p": "6", "6t": "", "7c": "10", "7p": "8", "7t": "", "8c": "", "8p": "", "8t": "", "total": "63"}, 
  {"pos": "9", "name": "Khan", "world": "Yak's Bend", "1c": "6", "1p": "7", "1t": "", "2c": "4", "2p": "14", "2t": "", "3c": "15", "3p": "5", "3t": "", "4c": "2", "4p": "14", "4t": "", "5c": "19", "5p": "1", "5t": "", "6c": "10", "6p": "5", "6t": "", "7c": "2", "7p": "14", "7t": "", "8c": "", "8p": "", "8t": "", "total": "58"}, 
  {"pos": "9", "name": "Tasmanian Devil", "world": "Gunnar's Hold", "1c": "9", "1p": "4", "1t": "", "2c": "11", "2p": "7", "2t": "", "3c": "14", "3p": "6", "3t": "", "4c": "21", "4p": "1", "4t": "", "5c": "3", "5p": "12", "5t": "", "6c": "", "6p": "", "6t": "", "7c": "", "7p": "", "7t": "", "8c": "", "8p": "", "8t": "", "total": "58"}, 
  {"pos": "10", "name": "Sylvester", "world": "Henge of Denravi", "1c": "10", "1p": "3", "1t": "", "2c": "12", "2p": "6", "2t": "", "3c": "10", "3p": "10", "3t": "", "4c": "14", "4p": "6", "4t": "", "5c": "9", "5p": "8", "5t": "", "6c": "", "6p": "", "6t": "", "7c": "", "7p": "", "7t": "", "8c": "", "8p": "", "8t": "", "total": "55"}, 
  {"pos": "10", "name": "Wally West", "world": "Underworld", "1c": "", "1p": "", "1t": "", "2c": "8", "2p": "10", "2t": "", "3c": "3", "3p": "15", "3t": "", "4c": "7", "4p": "11", "4t": "", "5c": "16", "5p": "2", "5t": "", "6c": "13", "6p": "3", "6t": "", "7c": "8", "7p": "10", "7t": "", "8c": "", "8p": "", "8t": "", "total": "55"}, 
  {"pos": "11", "name": "Blue Beetle", "world": "Ruins of Surmia", "1c": "", "1p": "", "1t": "", "2c": "15", "2p": "3", "2t": "", "3c": "9", "3p": "11", "3t": "", "4c": "5", "4p": "13", "4t": "", "5c": "13", "5p": "4", "5t": "", "6c": "7", "6p": "8", "6t": "", "7c": "5", "7p": "12", "7t": "", "8c": "", "8p": "", "8t": "", "total": "54"}, 
  {"pos": "12", "name": "Wonder Woman", "world": "Underworld", "1c": "", "1p": "", "1t": "", "2c": "9", "2p": "9", "2t": "", "3c": "12", "3p": "8", "3t": "", "4c": "", "4p": "", "4t": "", "5c": "10", "5p": "7", "5t": "", "6c": "14", "6p": "2", "6t": "", "7c": "8", "7p": "10", "7t": "", "8c": "", "8p": "", "8t": "", "total": "53"}, 
  {"pos": "13", "name": "Daffy Duck", "world": "Ruins of Surmia", "1c": "", "1p": "", "1t": "", "2c": "12", "2p": "6", "2t": "", "3c": "14", "3p": "6", "3t": "", "4c": "7", "4p": "11", "4t": "", "5c": "7", "5p": "9", "5t": "", "6c": "8", "6p": "7", "6t": "", "7c": "4", "7p": "13", "7t": "", "8c": "", "8p": "", "8t": "", "total": "52"}, 
  {"pos": "13", "name": "Legion", "world": "Yak's Bend", "1c": "8", "1p": "5", "1t": "", "2c": "7", "2p": "11", "2t": "", "3c": "14", "3p": "6", "3t": "", "4c": "9", "4p": "9", "4t": "", "5c": "", "5p": "", "5t": "", "6c": "10", "6p": "5", "6t": "", "7c": "4", "7p": "13", "7t": "", "8c": "", "8p": "", "8t": "", "total": "52"}, 
  {"pos": "14", "name": "Superman", "world": "Piken Square", "1c": "", "1p": "", "1t": "", "2c": "7", "2p": "11", "2t": "", "3c": "21", "3p": "1", "3t": "", "4c": "5", "4p": "13", "4t": "", "5c": "3", "5p": "12", "5t": "", "6c": "", "6p": "", "6t": "", "7c": "12", "7p": "6", "7t": "", "8c": "", "8p": "", "8t": "", "total": "48"}, 
  {"pos": "15", "name": "Elmer Fudd", "world": "Sea of Sorrows", "1c": "", "1p": "", "1t": "", "2c": "2", "2p": "16", "2t": "", "3c": "9", "3p": "11", "3t": "", "4c": "16", "4p": "4", "4t": "", "5c": "5", "5p": "11", "5t": "", "6c": "6", "6p": "9", "6t": "", "7c": "9", "7p": "9", "7t": "", "8c": "", "8p": "", "8t": "", "total": "47"}, 
  {"pos": "16", "name": "Nite Owl", "world": "Jade Sea", "1c": "6", "1p": "7", "1t": "", "2c": "11", "2p": "7", "2t": "", "3c": "19", "3p": "2", "3t": "", "4c": "7", "4p": "11", "4t": "", "5c": "1", "5p": "14", "5t": "", "6c": "", "6p": "", "6t": "", "7c": "", "7p": "", "7t": "", "8c": "", "8p": "", "8t": "", "total": "44"}, 
  {"pos": "17", "name": "Tigger", "world": "Riverside", "1c": "", "1p": "", "1t": "", "2c": "2", "2p": "16", "2t": "", "3c": "8", "3p": "12", "3t": "", "4c": "8", "4p": "10", "4t": "", "5c": "9", "5p": "8", "5t": "", "6c": "9", "6p": "6", "6t": "", "7c": "7", "7p": "11", "7t": "", "8c": "", "8p": "", "8t": "", "total": "43"}, 
  {"pos": "18", "name": "Nite Hawk", "world": "Kaineng", "1c": "9", "1p": "4", "1t": "", "2c": "10", "2p": "8", "2t": "", "3c": "8", "3p": "12", "3t": "", "4c": "12", "4p": "7", "4t": "", "5c": "3", "5p": "12", "5t": "", "6c": "", "6p": "", "6t": "", "7c": "", "7p": "", "7t": "", "8c": "", "8p": "", "8t": "", "total": "42"}, 
  {"pos": "19", "name": "Tim Drake", "world": "Underworld", "1c": "", "1p": "", "1t": "", "2c": "5", "2p": "13", "2t": "", "3c": "4", "3p": "14", "3t": "", "4c": "14", "4p": "6", "4t": "", "5c": "3", "5p": "12", "5t": "", "6c": "2", "6p": "11", "6t": "", "7c": "10", "7p": "8", "7t": "", "8c": "", "8p": "", "8t": "", "total": "38"}, 
  {"pos": "20", "name": "Pink Panther", "world": "Miller's Sound", "1c": "", "1p": "", "1t": "", "2c": "14", "2p": "4", "2t": "", "3c": "4", "3p": "14", "3t": "", "4c": "6", "4p": "12", "4t": "", "5c": "13", "5p": "4", "5t": "", "6c": "", "6p": "", "6t": "", "7c": "", "7p": "", "7t": "", "8c": "", "8p": "", "8t": "", "total": "37"}, 
  {"pos": "21", "name": "The Hulk", "world": "Seafarer's Rest", "1c": "", "1p": "", "1t": "", "2c": "", "2p": "", "2t": "", "3c": "", "3p": "", "3t": "", "4c": "", "4p": "", "4t": "", "5c": "", "5p": "", "5t": "", "6c": "13", "6p": "3", "6t": "", "7c": "10", "7p": "8", "7t": "", "8c": "", "8p": "", "8t": "", "total": "23"}, 
  {"pos": "22", "name": "biot.4721", "world": "Gandara", "1c": "", "1p": "", "1t": "", "2c": "2", "2p": "16", "2t": "", "3c": "4", "3p": "14", "3t": "", "4c": "", "4p": "", "4t": "", "5c": "1", "5p": "14", "5t": "", "6c": "2", "6p": "11", "6t": "", "7c": "12", "7p": "6", "7t": "", "8c": "", "8p": "", "8t": "", "total": "21"}, 
  {"pos": "23", "name": "Batman", "world": "Tarnished Coast", "1c": "", "1p": "", "1t": "", "2c": "", "2p": "", "2t": "", "3c": "", "3p": "", "3t": "", "4c": "", "4p": "", "4t": "", "5c": "", "5p": "", "5t": "", "6c": "9", "6p": "6", "6t": "", "7c": "10", "7p": "8", "7t": "", "8c": "", "8p": "", "8t": "", "total": "19"}, 
  {"pos": "24", "name": "Maggie Simpson", "world": "Sorrow's Furnace", "1c": "", "1p": "", "1t": "", "2c": "", "2p": "", "2t": "", "3c": "", "3p": "", "3t": "", "4c": "", "4p": "", "4t": "", "5c": "", "5p": "", "5t": "", "6c": "9", "6p": "6", "6t": "", "7c": "9", "7p": "9", "7t": "", "8c": "", "8p": "", "8t": "", "total": "18"}, 
  {"pos": "25", "name": "Marge Simpson", "world": "Stormbluff Isle", "1c": "", "1p": "", "1t": "", "2c": "", "2p": "", "2t": "", "3c": "", "3p": "", "3t": "", "4c": "", "4p": "", "4t": "", "5c": "", "5p": "", "5t": "", "6c": "2", "6p": "11", "6t": "", "7c": "12", "7p": "6", "7t": "", "8c": "", "8p": "", "8t": "", "total": "14"}, 
  {"pos": "26", "name": "Huey Duck", "world": "Fissure of Woe", "1c": "13", "1p": "1", "1t": "", "2c": "", "2p": "", "2t": "", "3c": "", "3p": "", "3t": "", "4c": "", "4p": "", "4t": "", "5c": "", "5p": "", "5t": "", "6c": "", "6p": "", "6t": "", "7c": "", "7p": "", "7t": "", "8c": "", "8p": "", "8t": "", "total": "13"}, 
  {"pos": "27", "name": "Beyond Justice", "world": "Underworld", "1c": "", "1p": "", "1t": "", "2c": "", "2p": "", "2t": "", "3c": "", "3p": "", "3t": "", "4c": "", "4p": "", "4t": "", "5c": "", "5p": "", "5t": "", "6c": "4", "6p": "10", "6t": "", "7c": "5", "7p": "12", "7t": "", "8c": "", "8p": "", "8t": "", "total": "9"}, 
  {"pos": "27", "name": "Minnie Mouse", "world": "Ferguson's Crossing", "1c": "9", "1p": "4", "1t": "", "2c": "", "2p": "", "2t": "", "3c": "", "3p": "", "3t": "", "4c": "", "4p": "", "4t": "", "5c": "", "5p": "", "5t": "", "6c": "", "6p": "", "6t": "", "7c": "", "7p": "", "7t": "", "8c": "", "8p": "", "8t": "", "total": "9"}, 
  {"pos": "28", "name": "Woody Woodpecker", "world": "Isle of Janthir", "1c": "8", "1p": "5", "1t": "", "2c": "", "2p": "", "2t": "", "3c": "", "3p": "", "3t": "", "4c": "", "4p": "", "4t": "", "5c": "", "5p": "", "5t": "", "6c": "", "6p": "", "6t": "", "7c": "", "7p": "", "7t": "", "8c": "", "8p": "", "8t": "", "total": "8"}, 
  {"pos": "29", "name": "Homer Simpson", "world": "Northern Shiverpeaks", "1c": "", "1p": "", "1t": "", "2c": "3", "2p": "15", "2t": "", "3c": "", "3p": "", "3t": "", "4c": "1", "4p": "15", "4t": "", "5c": "2", "5p": "13", "5t": "", "6c": "", "6p": "", "6t": "", "7c": "", "7p": "", "7t": "", "8c": "", "8p": "", "8t": "", "total": "6"}, 
  {"pos": "30", "name": "Barney Rubble", "world": "Gandara", "1c": "5", "1p": "8", "1t": "", "2c": "", "2p": "", "2t": "", "3c": "", "3p": "", "3t": "", "4c": "", "4p": "", "4t": "", "5c": "", "5p": "", "5t": "", "6c": "", "6p": "", "6t": "", "7c": "", "7p": "", "7t": "", "8c": "", "8p": "", "8t": "", "total": "5"}, 
  {"pos": "30", "name": "Bart", "world": "Jade Quarry", "1c": "5", "1p": "8", "1t": "", "2c": "", "2p": "", "2t": "", "3c": "", "3p": "", "3t": "", "4c": "", "4p": "", "4t": "", "5c": "", "5p": "", "5t": "", "6c": "", "6p": "", "6t": "", "7c": "", "7p": "", "7t": "", "8c": "", "8p": "", "8t": "", "total": "5"}, 
  {"pos": "31", "name": "Mario", "world": "Gate of Madness", "1c": "2", "1p": "9", "1t": "", "2c": "", "2p": "", "2t": "", "3c": "", "3p": "", "3t": "", "4c": "", "4p": "", "4t": "", "5c": "", "5p": "", "5t": "", "6c": "", "6p": "", "6t": "", "7c": "", "7p": "", "7t": "", "8c": "", "8p": "", "8t": "", "total": "2"}
],
"commentary": [
  {"comment": "1st place, with 88 kills in 3.5 hours of play is Fred Flintstone from Maguuma"},
  {"comment": "2nd place, with 83 kills in 3 hours of play is Kvothe from Yak's Bend"},
  {"comment": "2nd place, with 83 kills in 3.5 hours of play is Riker from Yak's Bend"},
  {"comment": "3rd place, with 80 kills in 3.5 hours of play is Bob the Dog from Yak's Bend"},
  {"comment": "Kvothe from Yak's Bend killed 23 in 30 minutes!"}
]
}
