{
"epoch": "1537451112", 
"datetime": "2018-09-20 13:45:12", 
"update_window": "1300-1359", 
"update_number": "08", 
"update_frequency": "60", 
"update_at": "13:45", 
"update_hourly_timestamp": "13:50", 
"update_daily_timestamp": "14:00", 
"update_weekly_timestamp": "14:45", 
"tournament": {
  "tournament_year": "2018", 
  "tournament_week": "37", 
  "tournament_day": "6", 
  "hour_filename": "T37-d6-hour", 
  "day_listing": "T37-d6 Wed Sep 19 18:00:00 UTC 2018 to Thu Sep 20 17:59:59 UTC 2018", 
  "day_title": "Tournament 37, Day 6", 
  "day_subtitle": "Wed Sep 19 18:00:00 UTC 2018 to Thu Sep 20 17:59:59 UTC 2018", 
  "day_filename": "T37-d6", 
  "day_url": "/tournaments/2018/09/19/T37-d6.html", 
  "week_listing": "Tournament 37", 
  "week_title": "Tournament 37", 
  "week_subtitle": "Fri Sep 14 18:00:00 UTC 2018 to Fri Sep 21 17:59:59 UTC 2018", 
  "week_filename": "T37", 
  "week_url": "/tournaments/2018/09/14/T37.html", 
  "schedule": [
    {"day": "1", "start": "Fri Sep 14 18:00:00 UTC 2018", "stop": "Sat Sep 15 17:59:59 UTC 2018"}, 
    {"day": "2", "start": "Sat Sep 15 18:00:00 UTC 2018", "stop": "Sun Sep 16 17:59:59 UTC 2018"}, 
    {"day": "3", "start": "Sun Sep 16 18:00:00 UTC 2018", "stop": "Mon Sep 17 17:59:59 UTC 2018"}, 
    {"day": "4", "start": "Mon Sep 17 18:00:00 UTC 2018", "stop": "Tue Sep 18 17:59:59 UTC 2018"}, 
    {"day": "5", "start": "Tue Sep 18 18:00:00 UTC 2018", "stop": "Wed Sep 19 17:59:59 UTC 2018"}, 
    {"day": "6", "start": "Wed Sep 19 18:00:00 UTC 2018", "stop": "Thu Sep 20 17:59:59 UTC 2018"}, 
    {"day": "7", "start": "Thu Sep 20 18:00:00 UTC 2018", "stop": "Fri Sep 21 17:59:59 UTC 2018"}
  ], 
},
"columns": [
  {"col": "COL1", "label": "01", "start": "Wed Sep 19 18:00:00 UTC 2018", "stop": "Wed Sep 19 18:59:59 UTC 2018", "url": ""},
  {"col": "COL2", "label": "02", "start": "Wed Sep 19 19:00:00 UTC 2018", "stop": "Wed Sep 19 19:59:59 UTC 2018", "url": ""},
  {"col": "COL3", "label": "03", "start": "Wed Sep 19 20:00:00 UTC 2018", "stop": "Wed Sep 19 20:59:59 UTC 2018", "url": ""},
  {"col": "COL4", "label": "04", "start": "Wed Sep 19 21:00:00 UTC 2018", "stop": "Wed Sep 19 21:59:59 UTC 2018", "url": ""},
  {"col": "COL5", "label": "05", "start": "Wed Sep 19 22:00:00 UTC 2018", "stop": "Wed Sep 19 22:59:59 UTC 2018", "url": ""},
  {"col": "COL6", "label": "06", "start": "Wed Sep 19 23:00:00 UTC 2018", "stop": "Wed Sep 19 23:59:59 UTC 2018", "url": ""},
  {"col": "COL7", "label": "07", "start": "Thu Sep 20 00:00:00 UTC 2018", "stop": "Thu Sep 20 00:59:59 UTC 2018", "url": ""},
  {"col": "COL8", "label": "08", "start": "Thu Sep 20 01:00:00 UTC 2018", "stop": "Thu Sep 20 01:59:59 UTC 2018", "url": ""},
  {"col": "COL9", "label": "09", "start": "Thu Sep 20 02:00:00 UTC 2018", "stop": "Thu Sep 20 02:59:59 UTC 2018", "url": ""},
  {"col": "COL10", "label": "10", "start": "Thu Sep 20 03:00:00 UTC 2018", "stop": "Thu Sep 20 03:59:59 UTC 2018", "url": ""},
  {"col": "COL11", "label": "11", "start": "Thu Sep 20 04:00:00 UTC 2018", "stop": "Thu Sep 20 04:59:59 UTC 2018", "url": ""},
  {"col": "COL12", "label": "12", "start": "Thu Sep 20 05:00:00 UTC 2018", "stop": "Thu Sep 20 05:59:59 UTC 2018", "url": ""},
  {"col": "COL13", "label": "13", "start": "Thu Sep 20 06:00:00 UTC 2018", "stop": "Thu Sep 20 06:59:59 UTC 2018", "url": ""},
  {"col": "COL14", "label": "14", "start": "Thu Sep 20 07:00:00 UTC 2018", "stop": "Thu Sep 20 07:59:59 UTC 2018", "url": ""},
  {"col": "COL15", "label": "15", "start": "Thu Sep 20 08:00:00 UTC 2018", "stop": "Thu Sep 20 08:59:59 UTC 2018", "url": ""},
  {"col": "COL16", "label": "16", "start": "Thu Sep 20 09:00:00 UTC 2018", "stop": "Thu Sep 20 09:59:59 UTC 2018", "url": ""},
  {"col": "COL17", "label": "17", "start": "Thu Sep 20 10:00:00 UTC 2018", "stop": "Thu Sep 20 10:59:59 UTC 2018", "url": ""},
  {"col": "COL18", "label": "18", "start": "Thu Sep 20 11:00:00 UTC 2018", "stop": "Thu Sep 20 11:59:59 UTC 2018", "url": ""},
  {"col": "COL19", "label": "19", "start": "Thu Sep 20 12:00:00 UTC 2018", "stop": "Thu Sep 20 12:59:59 UTC 2018", "url": ""},
  {"col": "COL20", "label": "20", "start": "Thu Sep 20 13:00:00 UTC 2018", "stop": "Thu Sep 20 13:59:59 UTC 2018", "url": ""},
  {"col": "COL21", "label": "21", "start": "Thu Sep 20 14:00:00 UTC 2018", "stop": "Thu Sep 20 14:59:59 UTC 2018", "url": ""},
  {"col": "COL22", "label": "22", "start": "Thu Sep 20 15:00:00 UTC 2018", "stop": "Thu Sep 20 15:59:59 UTC 2018", "url": ""},
  {"col": "COL23", "label": "23", "start": "Thu Sep 20 16:00:00 UTC 2018", "stop": "Thu Sep 20 16:59:59 UTC 2018", "url": ""},
  {"col": "COL24", "label": "24", "start": "Thu Sep 20 17:00:00 UTC 2018", "stop": "Thu Sep 20 17:59:59 UTC 2018", "url": ""}
],
"entries": [
  {"pos": "1", "name": "Bob the Dog", "world": "Yak's Bend", "1c": "29", "1p": "3", "2c": "23", "2p": "9", "3c": "40", "3p": "1", "4c": "32", "4p": "5", "5c": "22", "5p": "10", "6c": "20", "6p": "10", "7c": "", "7p": "", "8c": "", "8p": "", "9c": "", "9p": "", "10c": "", "10p": "", "11c": "", "11p": "", "12c": "", "12p": "", "13c": "", "13p": "", "14c": "", "14p": "", "15c": "", "15p": "", "16c": "", "16p": "", "17c": "", "17p": "", "18c": "16", "18p": "6", "19c": "9", "19p": "8", "20c": "14", "20p": "11", "21c": "", "21p": "", "22c": "", "22p": "", "23c": "", "23p": "", "24c": "", "24p": "", "total": "205"}, 
  {"pos": "2", "name": "Skritt Forager", "world": "Abaddon's Mouth", "1c": "", "1p": "", "2c": "", "2p": "", "3c": "", "3p": "", "4c": "", "4p": "", "5c": "", "5p": "", "6c": "", "6p": "", "7c": "32", "7p": "1", "8c": "23", "8p": "1", "9c": "25", "9p": "1", "10c": "23", "10p": "2", "11c": "29", "11p": "1", "12c": "38", "12p": "1", "13c": "25", "13p": "2", "14c": "", "14p": "", "15c": "", "15p": "", "16c": "", "16p": "", "17c": "", "17p": "", "18c": "", "18p": "", "19c": "", "19p": "", "20c": "", "20p": "", "21c": "", "21p": "", "22c": "", "22p": "", "23c": "", "23p": "", "24c": "", "24p": "", "total": "195"}, 
  {"pos": "3", "name": "Batgirl", "world": "Ruins of Surmia", "1c": "28", "1p": "4", "2c": "30", "2p": "3", "3c": "35", "3p": "2", "4c": "16", "4p": "16", "5c": "32", "5p": "2", "6c": "25", "6p": "7", "7c": "", "7p": "", "8c": "", "8p": "", "9c": "", "9p": "", "10c": "", "10p": "", "11c": "", "11p": "", "12c": "", "12p": "", "13c": "", "13p": "", "14c": "", "14p": "", "15c": "", "15p": "", "16c": "", "16p": "", "17c": "", "17p": "", "18c": "", "18p": "", "19c": "", "19p": "", "20c": "", "20p": "", "21c": "", "21p": "", "22c": "", "22p": "", "23c": "", "23p": "", "24c": "", "24p": "", "total": "166"}, 
  {"pos": "4", "name": "Wonder Woman", "world": "Underworld", "1c": "22", "1p": "9", "2c": "19", "2p": "12", "3c": "24", "3p": "9", "4c": "34", "4p": "3", "5c": "25", "5p": "7", "6c": "32", "6p": "2", "7c": "", "7p": "", "8c": "", "8p": "", "9c": "", "9p": "", "10c": "", "10p": "", "11c": "", "11p": "", "12c": "", "12p": "", "13c": "", "13p": "", "14c": "", "14p": "", "15c": "", "15p": "", "16c": "", "16p": "", "17c": "", "17p": "", "18c": "", "18p": "", "19c": "", "19p": "", "20c": "", "20p": "", "21c": "", "21p": "", "22c": "", "22p": "", "23c": "", "23p": "", "24c": "", "24p": "", "total": "156"}, 
  {"pos": "5", "name": "Goofy", "world": "Drakkar Lake", "1c": "", "1p": "", "2c": "", "2p": "", "3c": "", "3p": "", "4c": "", "4p": "", "5c": "", "5p": "", "6c": "", "6p": "", "7c": "", "7p": "", "8c": "", "8p": "", "9c": "", "9p": "", "10c": "", "10p": "", "11c": "", "11p": "", "12c": "", "12p": "", "13c": "", "13p": "", "14c": "", "14p": "", "15c": "20", "15p": "7", "16c": "27", "16p": "4", "17c": "34", "17p": "2", "18c": "27", "18p": "1", "19c": "18", "19p": "4", "20c": "28", "20p": "2", "21c": "", "21p": "", "22c": "", "22p": "", "23c": "", "23p": "", "24c": "", "24p": "", "total": "154"}, 
  {"pos": "6", "name": "Barbara Gordon", "world": "Ruins of Surmia", "1c": "23", "1p": "8", "2c": "29", "2p": "4", "3c": "23", "3p": "10", "4c": "34", "4p": "3", "5c": "23", "5p": "9", "6c": "21", "6p": "9", "7c": "", "7p": "", "8c": "", "8p": "", "9c": "", "9p": "", "10c": "", "10p": "", "11c": "", "11p": "", "12c": "", "12p": "", "13c": "", "13p": "", "14c": "", "14p": "", "15c": "", "15p": "", "16c": "", "16p": "", "17c": "", "17p": "", "18c": "", "18p": "", "19c": "", "19p": "", "20c": "", "20p": "", "21c": "", "21p": "", "22c": "", "22p": "", "23c": "", "23p": "", "24c": "", "24p": "", "total": "153"}, 
  {"pos": "7", "name": "Vic Sage", "world": "Underworld", "1c": "33", "1p": "1", "2c": "21", "2p": "10", "3c": "29", "3p": "6", "4c": "12", "4p": "18", "5c": "28", "5p": "4", "6c": "29", "6p": "4", "7c": "", "7p": "", "8c": "", "8p": "", "9c": "", "9p": "", "10c": "", "10p": "", "11c": "", "11p": "", "12c": "", "12p": "", "13c": "", "13p": "", "14c": "", "14p": "", "15c": "", "15p": "", "16c": "", "16p": "", "17c": "", "17p": "", "18c": "", "18p": "", "19c": "", "19p": "", "20c": "", "20p": "", "21c": "", "21p": "", "22c": "", "22p": "", "23c": "", "23p": "", "24c": "", "24p": "", "total": "152"}, 
  {"pos": "8", "name": "Tim Drake", "world": "Underworld", "1c": "23", "1p": "8", "2c": "28", "2p": "5", "3c": "27", "3p": "7", "4c": "20", "4p": "14", "5c": "26", "5p": "6", "6c": "27", "6p": "5", "7c": "", "7p": "", "8c": "", "8p": "", "9c": "", "9p": "", "10c": "", "10p": "", "11c": "", "11p": "", "12c": "", "12p": "", "13c": "", "13p": "", "14c": "", "14p": "", "15c": "", "15p": "", "16c": "", "16p": "", "17c": "", "17p": "", "18c": "", "18p": "", "19c": "", "19p": "", "20c": "", "20p": "", "21c": "", "21p": "", "22c": "", "22p": "", "23c": "", "23p": "", "24c": "", "24p": "", "total": "151"}, 
  {"pos": "9", "name": "Blue Beetle", "world": "Ruins of Surmia", "1c": "19", "1p": "10", "2c": "29", "2p": "4", "3c": "21", "3p": "12", "4c": "22", "4p": "12", "5c": "27", "5p": "5", "6c": "26", "6p": "6", "7c": "", "7p": "", "8c": "", "8p": "", "9c": "", "9p": "", "10c": "", "10p": "", "11c": "", "11p": "", "12c": "", "12p": "", "13c": "", "13p": "", "14c": "", "14p": "", "15c": "", "15p": "", "16c": "", "16p": "", "17c": "", "17p": "", "18c": "", "18p": "", "19c": "", "19p": "", "20c": "", "20p": "", "21c": "", "21p": "", "22c": "", "22p": "", "23c": "", "23p": "", "24c": "", "24p": "", "total": "144"}, 
  {"pos": "10", "name": "Wally West", "world": "Underworld", "1c": "18", "1p": "11", "2c": "27", "2p": "6", "3c": "30", "3p": "5", "4c": "30", "4p": "6", "5c": "20", "5p": "11", "6c": "16", "6p": "12", "7c": "", "7p": "", "8c": "", "8p": "", "9c": "", "9p": "", "10c": "", "10p": "", "11c": "", "11p": "", "12c": "", "12p": "", "13c": "", "13p": "", "14c": "", "14p": "", "15c": "", "15p": "", "16c": "", "16p": "", "17c": "", "17p": "", "18c": "", "18p": "", "19c": "", "19p": "", "20c": "", "20p": "", "21c": "", "21p": "", "22c": "", "22p": "", "23c": "", "23p": "", "24c": "", "24p": "", "total": "141"}, 
  {"pos": "11", "name": "Eric Cartman", "world": "Sanctum of Rall", "1c": "15", "1p": "12", "2c": "8", "2p": "16", "3c": "22", "3p": "11", "4c": "29", "4p": "7", "5c": "28", "5p": "4", "6c": "35", "6p": "1", "7c": "", "7p": "", "8c": "", "8p": "", "9c": "", "9p": "", "10c": "", "10p": "", "11c": "", "11p": "", "12c": "", "12p": "", "13c": "", "13p": "", "14c": "", "14p": "", "15c": "", "15p": "", "16c": "", "16p": "", "17c": "", "17p": "", "18c": "", "18p": "", "19c": "", "19p": "", "20c": "", "20p": "", "21c": "", "21p": "", "22c": "", "22p": "", "23c": "", "23p": "", "24c": "", "24p": "", "total": "137"}, 
  {"pos": "12", "name": "Elmer Fudd", "world": "Sea of Sorrows", "1c": "26", "1p": "6", "2c": "13", "2p": "14", "3c": "15", "3p": "15", "4c": "26", "4p": "9", "5c": "24", "5p": "8", "6c": "32", "6p": "2", "7c": "", "7p": "", "8c": "", "8p": "", "9c": "", "9p": "", "10c": "", "10p": "", "11c": "", "11p": "", "12c": "", "12p": "", "13c": "", "13p": "", "14c": "", "14p": "", "15c": "", "15p": "", "16c": "", "16p": "", "17c": "", "17p": "", "18c": "", "18p": "", "19c": "", "19p": "", "20c": "", "20p": "", "21c": "", "21p": "", "22c": "", "22p": "", "23c": "", "23p": "", "24c": "", "24p": "", "total": "136"}, 
  {"pos": "13", "name": "Daffy Duck", "world": "Ruins of Surmia", "1c": "15", "1p": "12", "2c": "27", "2p": "6", "3c": "21", "3p": "12", "4c": "32", "4p": "5", "5c": "23", "5p": "9", "6c": "17", "6p": "11", "7c": "", "7p": "", "8c": "", "8p": "", "9c": "", "9p": "", "10c": "", "10p": "", "11c": "", "11p": "", "12c": "", "12p": "", "13c": "", "13p": "", "14c": "", "14p": "", "15c": "", "15p": "", "16c": "", "16p": "", "17c": "", "17p": "", "18c": "", "18p": "", "19c": "", "19p": "", "20c": "", "20p": "", "21c": "", "21p": "", "22c": "", "22p": "", "23c": "", "23p": "", "24c": "", "24p": "", "total": "135"}, 
  {"pos": "14", "name": "The Joker", "world": "Blackgate", "1c": "32", "1p": "2", "2c": "21", "2p": "10", "3c": "30", "3p": "5", "4c": "32", "4p": "5", "5c": "19", "5p": "12", "6c": "", "6p": "", "7c": "", "7p": "", "8c": "", "8p": "", "9c": "", "9p": "", "10c": "", "10p": "", "11c": "", "11p": "", "12c": "", "12p": "", "13c": "", "13p": "", "14c": "", "14p": "", "15c": "", "15p": "", "16c": "", "16p": "", "17c": "", "17p": "", "18c": "", "18p": "", "19c": "", "19p": "", "20c": "", "20p": "", "21c": "", "21p": "", "22c": "", "22p": "", "23c": "", "23p": "", "24c": "", "24p": "", "total": "134"}, 
  {"pos": "15", "name": "Shiny!", "world": "Anvil Rock", "1c": "", "1p": "", "2c": "", "2p": "", "3c": "", "3p": "", "4c": "", "4p": "", "5c": "", "5p": "", "6c": "", "6p": "", "7c": "19", "7p": "2", "8c": "16", "8p": "2", "9c": "16", "9p": "2", "10c": "27", "10p": "1", "11c": "13", "11p": "2", "12c": "20", "12p": "2", "13c": "21", "13p": "3", "14c": "", "14p": "", "15c": "", "15p": "", "16c": "", "16p": "", "17c": "", "17p": "", "18c": "", "18p": "", "19c": "", "19p": "", "20c": "", "20p": "", "21c": "", "21p": "", "22c": "", "22p": "", "23c": "", "23p": "", "24c": "", "24p": "", "total": "132"}, 
  {"pos": "16", "name": "Khan", "world": "Yak's Bend", "1c": "27", "1p": "5", "2c": "26", "2p": "7", "3c": "24", "3p": "9", "4c": "38", "4p": "1", "5c": "", "5p": "", "6c": "", "6p": "", "7c": "", "7p": "", "8c": "", "8p": "", "9c": "", "9p": "", "10c": "", "10p": "", "11c": "", "11p": "", "12c": "", "12p": "", "13c": "", "13p": "", "14c": "", "14p": "", "15c": "", "15p": "", "16c": "", "16p": "", "17c": "", "17p": "", "18c": "", "18p": "", "19c": "", "19p": "", "20c": "", "20p": "", "21c": "", "21p": "", "22c": "", "22p": "", "23c": "", "23p": "", "24c": "", "24p": "", "total": "115"}, 
  {"pos": "17", "name": "Beyond Justice", "world": "Underworld", "1c": "", "1p": "", "2c": "", "2p": "", "3c": "31", "3p": "4", "4c": "33", "4p": "4", "5c": "25", "5p": "7", "6c": "23", "6p": "8", "7c": "", "7p": "", "8c": "", "8p": "", "9c": "", "9p": "", "10c": "", "10p": "", "11c": "", "11p": "", "12c": "", "12p": "", "13c": "", "13p": "", "14c": "", "14p": "", "15c": "", "15p": "", "16c": "", "16p": "", "17c": "", "17p": "", "18c": "", "18p": "", "19c": "", "19p": "", "20c": "", "20p": "", "21c": "", "21p": "", "22c": "", "22p": "", "23c": "", "23p": "", "24c": "", "24p": "", "total": "112"}, 
  {"pos": "17", "name": "Oh So Cute", "world": "Blacktide", "1c": "", "1p": "", "2c": "", "2p": "", "3c": "", "3p": "", "4c": "", "4p": "", "5c": "", "5p": "", "6c": "", "6p": "", "7c": "", "7p": "", "8c": "", "8p": "", "9c": "", "9p": "", "10c": "", "10p": "", "11c": "", "11p": "", "12c": "", "12p": "", "13c": "20", "13p": "4", "14c": "28", "14p": "2", "15c": "29", "15p": "3", "16c": "35", "16p": "2", "17c": "", "17p": "", "18c": "", "18p": "", "19c": "", "19p": "", "20c": "", "20p": "", "21c": "", "21p": "", "22c": "", "22p": "", "23c": "", "23p": "", "24c": "", "24p": "", "total": "112"}, 
  {"pos": "18", "name": "Fred Flintstone", "world": "Maguuma", "1c": "32", "1p": "2", "2c": "27", "2p": "6", "3c": "30", "3p": "5", "4c": "21", "4p": "13", "5c": "", "5p": "", "6c": "", "6p": "", "7c": "", "7p": "", "8c": "", "8p": "", "9c": "", "9p": "", "10c": "", "10p": "", "11c": "", "11p": "", "12c": "", "12p": "", "13c": "", "13p": "", "14c": "", "14p": "", "15c": "", "15p": "", "16c": "", "16p": "", "17c": "", "17p": "", "18c": "", "18p": "", "19c": "", "19p": "", "20c": "", "20p": "", "21c": "", "21p": "", "22c": "", "22p": "", "23c": "", "23p": "", "24c": "", "24p": "", "total": "110"}, 
  {"pos": "19", "name": "Daisy Duck", "world": "Dragonbrand", "1c": "", "1p": "", "2c": "", "2p": "", "3c": "", "3p": "", "4c": "", "4p": "", "5c": "", "5p": "", "6c": "", "6p": "", "7c": "", "7p": "", "8c": "", "8p": "", "9c": "", "9p": "", "10c": "", "10p": "", "11c": "", "11p": "", "12c": "", "12p": "", "13c": "", "13p": "", "14c": "", "14p": "", "15c": "33", "15p": "1", "16c": "14", "16p": "9", "17c": "43", "17p": "1", "18c": "19", "18p": "5", "19c": "", "19p": "", "20c": "", "20p": "", "21c": "", "21p": "", "22c": "", "22p": "", "23c": "", "23p": "", "24c": "", "24p": "", "total": "109"}, 
  {"pos": "20", "name": "Riker", "world": "Yak's Bend", "1c": "29", "1p": "3", "2c": "35", "2p": "2", "3c": "19", "3p": "14", "4c": "24", "4p": "10", "5c": "", "5p": "", "6c": "", "6p": "", "7c": "", "7p": "", "8c": "", "8p": "", "9c": "", "9p": "", "10c": "", "10p": "", "11c": "", "11p": "", "12c": "", "12p": "", "13c": "", "13p": "", "14c": "", "14p": "", "15c": "", "15p": "", "16c": "", "16p": "", "17c": "", "17p": "", "18c": "", "18p": "", "19c": "", "19p": "", "20c": "", "20p": "", "21c": "", "21p": "", "22c": "", "22p": "", "23c": "", "23p": "", "24c": "", "24p": "", "total": "107"}, 
  {"pos": "21", "name": "Donald Duck", "world": "Kodash", "1c": "19", "1p": "10", "2c": "23", "2p": "9", "3c": "34", "3p": "3", "4c": "28", "4p": "8", "5c": "", "5p": "", "6c": "", "6p": "", "7c": "", "7p": "", "8c": "", "8p": "", "9c": "", "9p": "", "10c": "", "10p": "", "11c": "", "11p": "", "12c": "", "12p": "", "13c": "", "13p": "", "14c": "", "14p": "", "15c": "", "15p": "", "16c": "", "16p": "", "17c": "", "17p": "", "18c": "", "18p": "", "19c": "", "19p": "", "20c": "", "20p": "", "21c": "", "21p": "", "22c": "", "22p": "", "23c": "", "23p": "", "24c": "", "24p": "", "total": "104"}, 
  {"pos": "22", "name": "Batman", "world": "Tarnished Coast", "1c": "", "1p": "", "2c": "", "2p": "", "3c": "19", "3p": "14", "4c": "37", "4p": "2", "5c": "25", "5p": "7", "6c": "21", "6p": "9", "7c": "", "7p": "", "8c": "", "8p": "", "9c": "", "9p": "", "10c": "", "10p": "", "11c": "", "11p": "", "12c": "", "12p": "", "13c": "", "13p": "", "14c": "", "14p": "", "15c": "", "15p": "", "16c": "", "16p": "", "17c": "", "17p": "", "18c": "", "18p": "", "19c": "", "19p": "", "20c": "", "20p": "", "21c": "", "21p": "", "22c": "", "22p": "", "23c": "", "23p": "", "24c": "", "24p": "", "total": "102"}, 
  {"pos": "22", "name": "Marge Simpson", "world": "Stormbluff Isle", "1c": "", "1p": "", "2c": "", "2p": "", "3c": "23", "3p": "10", "4c": "28", "4p": "8", "5c": "30", "5p": "3", "6c": "21", "6p": "9", "7c": "", "7p": "", "8c": "", "8p": "", "9c": "", "9p": "", "10c": "", "10p": "", "11c": "", "11p": "", "12c": "", "12p": "", "13c": "", "13p": "", "14c": "", "14p": "", "15c": "", "15p": "", "16c": "", "16p": "", "17c": "", "17p": "", "18c": "", "18p": "", "19c": "", "19p": "", "20c": "", "20p": "", "21c": "", "21p": "", "22c": "", "22p": "", "23c": "", "23p": "", "24c": "", "24p": "", "total": "102"}, 
  {"pos": "22", "name": "Nightwing", "world": "Blackgate", "1c": "", "1p": "", "2c": "", "2p": "", "3c": "", "3p": "", "4c": "", "4p": "", "5c": "", "5p": "", "6c": "", "6p": "", "7c": "", "7p": "", "8c": "", "8p": "", "9c": "", "9p": "", "10c": "", "10p": "", "11c": "", "11p": "", "12c": "", "12p": "", "13c": "", "13p": "", "14c": "", "14p": "", "15c": "", "15p": "", "16c": "", "16p": "", "17c": "25", "17p": "5", "18c": "20", "18p": "4", "19c": "22", "19p": "3", "20c": "35", "20p": "1", "21c": "", "21p": "", "22c": "", "22p": "", "23c": "", "23p": "", "24c": "", "24p": "", "total": "102"}, 
  {"pos": "23", "name": "All Action Hero", "world": "Blackgate", "1c": "", "1p": "", "2c": "", "2p": "", "3c": "", "3p": "", "4c": "", "4p": "", "5c": "", "5p": "", "6c": "", "6p": "", "7c": "", "7p": "", "8c": "", "8p": "", "9c": "", "9p": "", "10c": "", "10p": "", "11c": "", "11p": "", "12c": "", "12p": "", "13c": "36", "13p": "1", "14c": "28", "14p": "2", "15c": "17", "15p": "8", "16c": "18", "16p": "7", "17c": "", "17p": "", "18c": "", "18p": "", "19c": "", "19p": "", "20c": "", "20p": "", "21c": "", "21p": "", "22c": "", "22p": "", "23c": "", "23p": "", "24c": "", "24p": "", "total": "99"}, 
  {"pos": "24", "name": "We Are Bob", "world": "Yak's Bend", "1c": "29", "1p": "3", "2c": "21", "2p": "10", "3c": "20", "3p": "13", "4c": "28", "4p": "8", "5c": "", "5p": "", "6c": "", "6p": "", "7c": "", "7p": "", "8c": "", "8p": "", "9c": "", "9p": "", "10c": "", "10p": "", "11c": "", "11p": "", "12c": "", "12p": "", "13c": "", "13p": "", "14c": "", "14p": "", "15c": "", "15p": "", "16c": "", "16p": "", "17c": "", "17p": "", "18c": "", "18p": "", "19c": "", "19p": "", "20c": "", "20p": "", "21c": "", "21p": "", "22c": "", "22p": "", "23c": "", "23p": "", "24c": "", "24p": "", "total": "98"}, 
  {"pos": "25", "name": "Homer", "world": "Yak's Bend", "1c": "28", "1p": "4", "2c": "20", "2p": "11", "3c": "27", "3p": "7", "4c": "22", "4p": "12", "5c": "", "5p": "", "6c": "", "6p": "", "7c": "", "7p": "", "8c": "", "8p": "", "9c": "", "9p": "", "10c": "", "10p": "", "11c": "", "11p": "", "12c": "", "12p": "", "13c": "", "13p": "", "14c": "", "14p": "", "15c": "", "15p": "", "16c": "", "16p": "", "17c": "", "17p": "", "18c": "", "18p": "", "19c": "", "19p": "", "20c": "", "20p": "", "21c": "", "21p": "", "22c": "", "22p": "", "23c": "", "23p": "", "24c": "", "24p": "", "total": "97"}, 
  {"pos": "26", "name": "E'telekeli", "world": "Borlis Pass", "1c": "", "1p": "", "2c": "", "2p": "", "3c": "", "3p": "", "4c": "", "4p": "", "5c": "", "5p": "", "6c": "", "6p": "", "7c": "", "7p": "", "8c": "", "8p": "", "9c": "", "9p": "", "10c": "", "10p": "", "11c": "", "11p": "", "12c": "", "12p": "", "13c": "", "13p": "", "14c": "27", "14p": "3", "15c": "30", "15p": "2", "16c": "39", "16p": "1", "17c": "", "17p": "", "18c": "", "18p": "", "19c": "", "19p": "", "20c": "", "20p": "", "21c": "", "21p": "", "22c": "", "22p": "", "23c": "", "23p": "", "24c": "", "24p": "", "total": "96"}, 
  {"pos": "27", "name": "Legion", "world": "Yak's Bend", "1c": "18", "1p": "11", "2c": "36", "2p": "1", "3c": "22", "3p": "11", "4c": "19", "4p": "15", "5c": "", "5p": "", "6c": "", "6p": "", "7c": "", "7p": "", "8c": "", "8p": "", "9c": "", "9p": "", "10c": "", "10p": "", "11c": "", "11p": "", "12c": "", "12p": "", "13c": "", "13p": "", "14c": "", "14p": "", "15c": "", "15p": "", "16c": "", "16p": "", "17c": "", "17p": "", "18c": "", "18p": "", "19c": "", "19p": "", "20c": "", "20p": "", "21c": "", "21p": "", "22c": "", "22p": "", "23c": "", "23p": "", "24c": "", "24p": "", "total": "95"}, 
  {"pos": "28", "name": "Oliver Queen", "world": "Blackgate", "1c": "", "1p": "", "2c": "", "2p": "", "3c": "", "3p": "", "4c": "", "4p": "", "5c": "", "5p": "", "6c": "", "6p": "", "7c": "", "7p": "", "8c": "", "8p": "", "9c": "", "9p": "", "10c": "", "10p": "", "11c": "", "11p": "", "12c": "", "12p": "", "13c": "", "13p": "", "14c": "", "14p": "", "15c": "", "15p": "", "16c": "", "16p": "", "17c": "29", "17p": "4", "18c": "24", "18p": "3", "19c": "26", "19p": "2", "20c": "15", "20p": "10", "21c": "", "21p": "", "22c": "", "22p": "", "23c": "", "23p": "", "24c": "", "24p": "", "total": "94"}, 
  {"pos": "28", "name": "Quaggan", "world": "Crystal Desert", "1c": "", "1p": "", "2c": "", "2p": "", "3c": "", "3p": "", "4c": "", "4p": "", "5c": "", "5p": "", "6c": "", "6p": "", "7c": "", "7p": "", "8c": "", "8p": "", "9c": "", "9p": "", "10c": "", "10p": "", "11c": "", "11p": "", "12c": "", "12p": "", "13c": "", "13p": "", "14c": "31", "14p": "1", "15c": "27", "15p": "5", "16c": "19", "16p": "6", "17c": "17", "17p": "6", "18c": "", "18p": "", "19c": "", "19p": "", "20c": "", "20p": "", "21c": "", "21p": "", "22c": "", "22p": "", "23c": "", "23p": "", "24c": "", "24p": "", "total": "94"}, 
  {"pos": "29", "name": "Superman", "world": "Piken Square", "1c": "24", "1p": "7", "2c": "19", "2p": "12", "3c": "22", "3p": "11", "4c": "28", "4p": "8", "5c": "", "5p": "", "6c": "", "6p": "", "7c": "", "7p": "", "8c": "", "8p": "", "9c": "", "9p": "", "10c": "", "10p": "", "11c": "", "11p": "", "12c": "", "12p": "", "13c": "", "13p": "", "14c": "", "14p": "", "15c": "", "15p": "", "16c": "", "16p": "", "17c": "", "17p": "", "18c": "", "18p": "", "19c": "", "19p": "", "20c": "", "20p": "", "21c": "", "21p": "", "22c": "", "22p": "", "23c": "", "23p": "", "24c": "", "24p": "", "total": "93"}, 
  {"pos": "30", "name": "Kvothe", "world": "Yak's Bend", "1c": "27", "1p": "5", "2c": "25", "2p": "8", "3c": "22", "3p": "11", "4c": "16", "4p": "16", "5c": "", "5p": "", "6c": "", "6p": "", "7c": "", "7p": "", "8c": "", "8p": "", "9c": "", "9p": "", "10c": "", "10p": "", "11c": "", "11p": "", "12c": "", "12p": "", "13c": "", "13p": "", "14c": "", "14p": "", "15c": "", "15p": "", "16c": "", "16p": "", "17c": "", "17p": "", "18c": "", "18p": "", "19c": "", "19p": "", "20c": "", "20p": "", "21c": "", "21p": "", "22c": "", "22p": "", "23c": "", "23p": "", "24c": "", "24p": "", "total": "90"}, 
  {"pos": "31", "name": "Stitch!", "world": "Ring of Fire", "1c": "26", "1p": "6", "2c": "20", "2p": "11", "3c": "13", "3p": "16", "4c": "26", "4p": "9", "5c": "", "5p": "", "6c": "", "6p": "", "7c": "", "7p": "", "8c": "", "8p": "", "9c": "", "9p": "", "10c": "", "10p": "", "11c": "", "11p": "", "12c": "", "12p": "", "13c": "", "13p": "", "14c": "", "14p": "", "15c": "", "15p": "", "16c": "", "16p": "", "17c": "", "17p": "", "18c": "", "18p": "", "19c": "", "19p": "", "20c": "", "20p": "", "21c": "", "21p": "", "22c": "", "22p": "", "23c": "", "23p": "", "24c": "", "24p": "", "total": "85"}, 
  {"pos": "32", "name": "Mickey Mouse", "world": "Devona's Rest", "1c": "", "1p": "", "2c": "", "2p": "", "3c": "", "3p": "", "4c": "", "4p": "", "5c": "", "5p": "", "6c": "", "6p": "", "7c": "", "7p": "", "8c": "", "8p": "", "9c": "", "9p": "", "10c": "", "10p": "", "11c": "", "11p": "", "12c": "", "12p": "", "13c": "", "13p": "", "14c": "", "14p": "", "15c": "28", "15p": "4", "16c": "15", "16p": "8", "17c": "14", "17p": "7", "18c": "26", "18p": "2", "19c": "", "19p": "", "20c": "", "20p": "", "21c": "", "21p": "", "22c": "", "22p": "", "23c": "", "23p": "", "24c": "", "24p": "", "total": "83"}, 
  {"pos": "33", "name": "Pepe Le Pew", "world": "Vizunah Square", "1c": "", "1p": "", "2c": "", "2p": "", "3c": "", "3p": "", "4c": "", "4p": "", "5c": "39", "5p": "1", "6c": "30", "6p": "3", "7c": "", "7p": "", "8c": "", "8p": "", "9c": "", "9p": "", "10c": "", "10p": "", "11c": "", "11p": "", "12c": "", "12p": "", "13c": "", "13p": "", "14c": "", "14p": "", "15c": "", "15p": "", "16c": "", "16p": "", "17c": "", "17p": "", "18c": "", "18p": "", "19c": "", "19p": "", "20c": "", "20p": "", "21c": "", "21p": "", "22c": "", "22p": "", "23c": "", "23p": "", "24c": "", "24p": "", "total": "69"}, 
  {"pos": "34", "name": "Tigger", "world": "Riverside", "1c": "22", "1p": "9", "2c": "10", "2p": "15", "3c": "22", "3p": "11", "4c": "11", "4p": "19", "5c": "", "5p": "", "6c": "", "6p": "", "7c": "", "7p": "", "8c": "", "8p": "", "9c": "", "9p": "", "10c": "", "10p": "", "11c": "", "11p": "", "12c": "", "12p": "", "13c": "", "13p": "", "14c": "", "14p": "", "15c": "", "15p": "", "16c": "", "16p": "", "17c": "", "17p": "", "18c": "", "18p": "", "19c": "", "19p": "", "20c": "", "20p": "", "21c": "", "21p": "", "22c": "", "22p": "", "23c": "", "23p": "", "24c": "", "24p": "", "total": "65"}, 
  {"pos": "35", "name": "Nite Hawk", "world": "Kaineng", "1c": "22", "1p": "9", "2c": "36", "2p": "1", "3c": "", "3p": "", "4c": "", "4p": "", "5c": "", "5p": "", "6c": "", "6p": "", "7c": "", "7p": "", "8c": "", "8p": "", "9c": "", "9p": "", "10c": "", "10p": "", "11c": "", "11p": "", "12c": "", "12p": "", "13c": "", "13p": "", "14c": "", "14p": "", "15c": "", "15p": "", "16c": "", "16p": "", "17c": "", "17p": "", "18c": "", "18p": "", "19c": "", "19p": "", "20c": "", "20p": "", "21c": "", "21p": "", "22c": "", "22p": "", "23c": "", "23p": "", "24c": "", "24p": "", "total": "58"}, 
  {"pos": "35", "name": "Pink Panther", "world": "Miller's Sound", "1c": "28", "1p": "4", "2c": "30", "2p": "3", "3c": "", "3p": "", "4c": "", "4p": "", "5c": "", "5p": "", "6c": "", "6p": "", "7c": "", "7p": "", "8c": "", "8p": "", "9c": "", "9p": "", "10c": "", "10p": "", "11c": "", "11p": "", "12c": "", "12p": "", "13c": "", "13p": "", "14c": "", "14p": "", "15c": "", "15p": "", "16c": "", "16p": "", "17c": "", "17p": "", "18c": "", "18p": "", "19c": "", "19p": "", "20c": "", "20p": "", "21c": "", "21p": "", "22c": "", "22p": "", "23c": "", "23p": "", "24c": "", "24p": "", "total": "58"}, 
  {"pos": "36", "name": "Road Runner", "world": "Elona Reach", "1c": "", "1p": "", "2c": "", "2p": "", "3c": "", "3p": "", "4c": "", "4p": "", "5c": "", "5p": "", "6c": "", "6p": "", "7c": "", "7p": "", "8c": "", "8p": "", "9c": "", "9p": "", "10c": "", "10p": "", "11c": "", "11p": "", "12c": "", "12p": "", "13c": "", "13p": "", "14c": "", "14p": "", "15c": "", "15p": "", "16c": "", "16p": "", "17c": "", "17p": "", "18c": "", "18p": "", "19c": "28", "19p": "1", "20c": "25", "20p": "4", "21c": "", "21p": "", "22c": "", "22p": "", "23c": "", "23p": "", "24c": "", "24p": "", "total": "53"}, 
  {"pos": "37", "name": "Hoohoo Heehee", "world": "Darkhaven", "1c": "", "1p": "", "2c": "", "2p": "", "3c": "", "3p": "", "4c": "", "4p": "", "5c": "", "5p": "", "6c": "", "6p": "", "7c": "", "7p": "", "8c": "", "8p": "", "9c": "", "9p": "", "10c": "", "10p": "", "11c": "", "11p": "", "12c": "", "12p": "", "13c": "", "13p": "", "14c": "", "14p": "", "15c": "26", "15p": "6", "16c": "25", "16p": "5", "17c": "", "17p": "", "18c": "", "18p": "", "19c": "", "19p": "", "20c": "", "20p": "", "21c": "", "21p": "", "22c": "", "22p": "", "23c": "", "23p": "", "24c": "", "24p": "", "total": "51"}, 
  {"pos": "38", "name": "Bart Simpson", "world": "Yak's Bend", "1c": "", "1p": "", "2c": "", "2p": "", "3c": "", "3p": "", "4c": "", "4p": "", "5c": "27", "5p": "5", "6c": "23", "6p": "8", "7c": "", "7p": "", "8c": "", "8p": "", "9c": "", "9p": "", "10c": "", "10p": "", "11c": "", "11p": "", "12c": "", "12p": "", "13c": "", "13p": "", "14c": "", "14p": "", "15c": "", "15p": "", "16c": "", "16p": "", "17c": "", "17p": "", "18c": "", "18p": "", "19c": "", "19p": "", "20c": "", "20p": "", "21c": "", "21p": "", "22c": "", "22p": "", "23c": "", "23p": "", "24c": "", "24p": "", "total": "50"}, 
  {"pos": "39", "name": "Tasmanian Devil", "world": "Gunnar's Hold", "1c": "19", "1p": "10", "2c": "30", "2p": "3", "3c": "", "3p": "", "4c": "", "4p": "", "5c": "", "5p": "", "6c": "", "6p": "", "7c": "", "7p": "", "8c": "", "8p": "", "9c": "", "9p": "", "10c": "", "10p": "", "11c": "", "11p": "", "12c": "", "12p": "", "13c": "", "13p": "", "14c": "", "14p": "", "15c": "", "15p": "", "16c": "", "16p": "", "17c": "", "17p": "", "18c": "", "18p": "", "19c": "", "19p": "", "20c": "", "20p": "", "21c": "", "21p": "", "22c": "", "22p": "", "23c": "", "23p": "", "24c": "", "24p": "", "total": "49"}, 
  {"pos": "40", "name": "Lightning Bug", "world": "Arborstone", "1c": "", "1p": "", "2c": "", "2p": "", "3c": "", "3p": "", "4c": "", "4p": "", "5c": "", "5p": "", "6c": "", "6p": "", "7c": "", "7p": "", "8c": "", "8p": "", "9c": "", "9p": "", "10c": "", "10p": "", "11c": "", "11p": "", "12c": "", "12p": "", "13c": "", "13p": "", "14c": "", "14p": "", "15c": "", "15p": "", "16c": "31", "16p": "3", "17c": "17", "17p": "6", "18c": "", "18p": "", "19c": "", "19p": "", "20c": "", "20p": "", "21c": "", "21p": "", "22c": "", "22p": "", "23c": "", "23p": "", "24c": "", "24p": "", "total": "48"}, 
  {"pos": "40", "name": "Maggie Simpson", "world": "Sorrow's Furnace", "1c": "", "1p": "", "2c": "", "2p": "", "3c": "25", "3p": "8", "4c": "23", "4p": "11", "5c": "", "5p": "", "6c": "", "6p": "", "7c": "", "7p": "", "8c": "", "8p": "", "9c": "", "9p": "", "10c": "", "10p": "", "11c": "", "11p": "", "12c": "", "12p": "", "13c": "", "13p": "", "14c": "", "14p": "", "15c": "", "15p": "", "16c": "", "16p": "", "17c": "", "17p": "", "18c": "", "18p": "", "19c": "", "19p": "", "20c": "", "20p": "", "21c": "", "21p": "", "22c": "", "22p": "", "23c": "", "23p": "", "24c": "", "24p": "", "total": "48"}, 
  {"pos": "41", "name": "Janie's Got a Gun", "world": "Desolation", "1c": "", "1p": "", "2c": "", "2p": "", "3c": "", "3p": "", "4c": "", "4p": "", "5c": "", "5p": "", "6c": "", "6p": "", "7c": "", "7p": "", "8c": "", "8p": "", "9c": "", "9p": "", "10c": "", "10p": "", "11c": "", "11p": "", "12c": "", "12p": "", "13c": "", "13p": "", "14c": "", "14p": "", "15c": "27", "15p": "5", "16c": "19", "16p": "6", "17c": "", "17p": "", "18c": "", "18p": "", "19c": "", "19p": "", "20c": "", "20p": "", "21c": "", "21p": "", "22c": "", "22p": "", "23c": "", "23p": "", "24c": "", "24p": "", "total": "46"}, 
  {"pos": "42", "name": "Cry of Frustration", "world": "Augury Rock", "1c": "", "1p": "", "2c": "", "2p": "", "3c": "", "3p": "", "4c": "", "4p": "", "5c": "", "5p": "", "6c": "", "6p": "", "7c": "", "7p": "", "8c": "", "8p": "", "9c": "", "9p": "", "10c": "", "10p": "", "11c": "", "11p": "", "12c": "", "12p": "", "13c": "", "13p": "", "14c": "", "14p": "", "15c": "", "15p": "", "16c": "13", "16p": "10", "17c": "32", "17p": "3", "18c": "", "18p": "", "19c": "", "19p": "", "20c": "", "20p": "", "21c": "", "21p": "", "22c": "", "22p": "", "23c": "", "23p": "", "24c": "", "24p": "", "total": "45"}, 
  {"pos": "43", "name": "Chip 'n' Dale", "world": "Vabbi", "1c": "", "1p": "", "2c": "", "2p": "", "3c": "", "3p": "", "4c": "", "4p": "", "5c": "24", "5p": "8", "6c": "20", "6p": "10", "7c": "", "7p": "", "8c": "", "8p": "", "9c": "", "9p": "", "10c": "", "10p": "", "11c": "", "11p": "", "12c": "", "12p": "", "13c": "", "13p": "", "14c": "", "14p": "", "15c": "", "15p": "", "16c": "", "16p": "", "17c": "", "17p": "", "18c": "", "18p": "", "19c": "", "19p": "", "20c": "", "20p": "", "21c": "", "21p": "", "22c": "", "22p": "", "23c": "", "23p": "", "24c": "", "24p": "", "total": "44"}, 
  {"pos": "44", "name": "Starman", "world": "Blackgate", "1c": "", "1p": "", "2c": "", "2p": "", "3c": "", "3p": "", "4c": "", "4p": "", "5c": "", "5p": "", "6c": "", "6p": "", "7c": "", "7p": "", "8c": "", "8p": "", "9c": "", "9p": "", "10c": "", "10p": "", "11c": "", "11p": "", "12c": "", "12p": "", "13c": "", "13p": "", "14c": "", "14p": "", "15c": "", "15p": "", "16c": "", "16p": "", "17c": "", "17p": "", "18c": "", "18p": "", "19c": "26", "19p": "2", "20c": "16", "20p": "9", "21c": "", "21p": "", "22c": "", "22p": "", "23c": "", "23p": "", "24c": "", "24p": "", "total": "42"}, 
  {"pos": "45", "name": "Yogi Bear", "world": "Far Shiverpeaks", "1c": "", "1p": "", "2c": "", "2p": "", "3c": "", "3p": "", "4c": "", "4p": "", "5c": "", "5p": "", "6c": "", "6p": "", "7c": "", "7p": "", "8c": "", "8p": "", "9c": "", "9p": "", "10c": "", "10p": "", "11c": "", "11p": "", "12c": "", "12p": "", "13c": "", "13p": "", "14c": "", "14p": "", "15c": "", "15p": "", "16c": "", "16p": "", "17c": "", "17p": "", "18c": "", "18p": "", "19c": "12", "19p": "7", "20c": "27", "20p": "3", "21c": "", "21p": "", "22c": "", "22p": "", "23c": "", "23p": "", "24c": "", "24p": "", "total": "39"}, 
  {"pos": "46", "name": "biot.4721", "world": "Gandara", "1c": "2", "1p": "14", "2c": "7", "2p": "17", "3c": "29", "3p": "6", "4c": "", "4p": "", "5c": "", "5p": "", "6c": "", "6p": "", "7c": "", "7p": "", "8c": "", "8p": "", "9c": "", "9p": "", "10c": "", "10p": "", "11c": "", "11p": "", "12c": "", "12p": "", "13c": "", "13p": "", "14c": "", "14p": "", "15c": "", "15p": "", "16c": "", "16p": "", "17c": "", "17p": "", "18c": "", "18p": "", "19c": "", "19p": "", "20c": "", "20p": "", "21c": "", "21p": "", "22c": "", "22p": "", "23c": "", "23p": "", "24c": "", "24p": "", "total": "38"}, 
  {"pos": "47", "name": "The Hulk", "world": "Seafarer's Rest", "1c": "", "1p": "", "2c": "", "2p": "", "3c": "21", "3p": "12", "4c": "15", "4p": "17", "5c": "", "5p": "", "6c": "", "6p": "", "7c": "", "7p": "", "8c": "", "8p": "", "9c": "", "9p": "", "10c": "", "10p": "", "11c": "", "11p": "", "12c": "", "12p": "", "13c": "", "13p": "", "14c": "", "14p": "", "15c": "", "15p": "", "16c": "", "16p": "", "17c": "", "17p": "", "18c": "", "18p": "", "19c": "", "19p": "", "20c": "", "20p": "", "21c": "", "21p": "", "22c": "", "22p": "", "23c": "", "23p": "", "24c": "", "24p": "", "total": "36"}, 
  {"pos": "48", "name": "Minnie Mouse", "world": "Ferguson's Crossing", "1c": "", "1p": "", "2c": "", "2p": "", "3c": "", "3p": "", "4c": "", "4p": "", "5c": "", "5p": "", "6c": "", "6p": "", "7c": "", "7p": "", "8c": "", "8p": "", "9c": "", "9p": "", "10c": "", "10p": "", "11c": "", "11p": "", "12c": "", "12p": "", "13c": "", "13p": "", "14c": "", "14p": "", "15c": "", "15p": "", "16c": "", "16p": "", "17c": "", "17p": "", "18c": "", "18p": "", "19c": "12", "19p": "7", "20c": "22", "20p": "5", "21c": "", "21p": "", "22c": "", "22p": "", "23c": "", "23p": "", "24c": "", "24p": "", "total": "34"}, 
  {"pos": "49", "name": "Darth Maul", "world": "Aurora Glade", "1c": "", "1p": "", "2c": "", "2p": "", "3c": "", "3p": "", "4c": "", "4p": "", "5c": "", "5p": "", "6c": "", "6p": "", "7c": "", "7p": "", "8c": "", "8p": "", "9c": "", "9p": "", "10c": "", "10p": "", "11c": "", "11p": "", "12c": "", "12p": "", "13c": "16", "13p": "5", "14c": "17", "14p": "4", "15c": "", "15p": "", "16c": "", "16p": "", "17c": "", "17p": "", "18c": "", "18p": "", "19c": "", "19p": "", "20c": "", "20p": "", "21c": "", "21p": "", "22c": "", "22p": "", "23c": "", "23p": "", "24c": "", "24p": "", "total": "33"}, 
  {"pos": "50", "name": "Superman", "world": "Blackgate", "1c": "", "1p": "", "2c": "", "2p": "", "3c": "", "3p": "", "4c": "", "4p": "", "5c": "", "5p": "", "6c": "", "6p": "", "7c": "", "7p": "", "8c": "", "8p": "", "9c": "", "9p": "", "10c": "", "10p": "", "11c": "", "11p": "", "12c": "", "12p": "", "13c": "", "13p": "", "14c": "", "14p": "", "15c": "", "15p": "", "16c": "", "16p": "", "17c": "", "17p": "", "18c": "", "18p": "", "19c": "15", "19p": "6", "20c": "17", "20p": "8", "21c": "", "21p": "", "22c": "", "22p": "", "23c": "", "23p": "", "24c": "", "24p": "", "total": "32"}, 
  {"pos": "51", "name": "Garfield", "world": "Ehmry Bay", "1c": "", "1p": "", "2c": "", "2p": "", "3c": "", "3p": "", "4c": "", "4p": "", "5c": "", "5p": "", "6c": "", "6p": "", "7c": "", "7p": "", "8c": "", "8p": "", "9c": "", "9p": "", "10c": "", "10p": "", "11c": "", "11p": "", "12c": "", "12p": "", "13c": "", "13p": "", "14c": "", "14p": "", "15c": "", "15p": "", "16c": "", "16p": "", "17c": "", "17p": "", "18c": "", "18p": "", "19c": "17", "19p": "5", "20c": "13", "20p": "12", "21c": "", "21p": "", "22c": "", "22p": "", "23c": "", "23p": "", "24c": "", "24p": "", "total": "30"}, 
  {"pos": "52", "name": "Piglet", "world": "Whiteside Ridge", "1c": "", "1p": "", "2c": "", "2p": "", "3c": "", "3p": "", "4c": "", "4p": "", "5c": "13", "5p": "13", "6c": "15", "6p": "13", "7c": "", "7p": "", "8c": "", "8p": "", "9c": "", "9p": "", "10c": "", "10p": "", "11c": "", "11p": "", "12c": "", "12p": "", "13c": "", "13p": "", "14c": "", "14p": "", "15c": "", "15p": "", "16c": "", "16p": "", "17c": "", "17p": "", "18c": "", "18p": "", "19c": "", "19p": "", "20c": "", "20p": "", "21c": "", "21p": "", "22c": "", "22p": "", "23c": "", "23p": "", "24c": "", "24p": "", "total": "28"}, 
  {"pos": "52", "name": "Sylvester", "world": "Henge of Denravi", "1c": "12", "1p": "13", "2c": "16", "2p": "13", "3c": "", "3p": "", "4c": "", "4p": "", "5c": "", "5p": "", "6c": "", "6p": "", "7c": "", "7p": "", "8c": "", "8p": "", "9c": "", "9p": "", "10c": "", "10p": "", "11c": "", "11p": "", "12c": "", "12p": "", "13c": "", "13p": "", "14c": "", "14p": "", "15c": "", "15p": "", "16c": "", "16p": "", "17c": "", "17p": "", "18c": "", "18p": "", "19c": "", "19p": "", "20c": "", "20p": "", "21c": "", "21p": "", "22c": "", "22p": "", "23c": "", "23p": "", "24c": "", "24p": "", "total": "28"}, 
  {"pos": "53", "name": "Spider Man", "world": "Eredon Terrace", "1c": "", "1p": "", "2c": "", "2p": "", "3c": "", "3p": "", "4c": "", "4p": "", "5c": "", "5p": "", "6c": "", "6p": "", "7c": "", "7p": "", "8c": "", "8p": "", "9c": "", "9p": "", "10c": "", "10p": "", "11c": "", "11p": "", "12c": "", "12p": "", "13c": "", "13p": "", "14c": "", "14p": "", "15c": "", "15p": "", "16c": "", "16p": "", "17c": "", "17p": "", "18c": "", "18p": "", "19c": "7", "19p": "9", "20c": "19", "20p": "6", "21c": "", "21p": "", "22c": "", "22p": "", "23c": "", "23p": "", "24c": "", "24p": "", "total": "26"}, 
  {"pos": "54", "name": "Louie Duck", "world": "Fort Ranik", "1c": "", "1p": "", "2c": "", "2p": "", "3c": "", "3p": "", "4c": "", "4p": "", "5c": "", "5p": "", "6c": "", "6p": "", "7c": "", "7p": "", "8c": "", "8p": "", "9c": "", "9p": "", "10c": "", "10p": "", "11c": "", "11p": "", "12c": "", "12p": "", "13c": "", "13p": "", "14c": "", "14p": "", "15c": "", "15p": "", "16c": "", "16p": "", "17c": "", "17p": "", "18c": "", "18p": "", "19c": "", "19p": "", "20c": "18", "20p": "7", "21c": "", "21p": "", "22c": "", "22p": "", "23c": "", "23p": "", "24c": "", "24p": "", "total": "18"}, 
  {"pos": "55", "name": "Dewey Duck", "world": "Fort Aspenwood", "1c": "", "1p": "", "2c": "", "2p": "", "3c": "", "3p": "", "4c": "", "4p": "", "5c": "", "5p": "", "6c": "", "6p": "", "7c": "", "7p": "", "8c": "", "8p": "", "9c": "", "9p": "", "10c": "", "10p": "", "11c": "", "11p": "", "12c": "", "12p": "", "13c": "", "13p": "", "14c": "", "14p": "", "15c": "", "15p": "", "16c": "", "16p": "", "17c": "", "17p": "", "18c": "", "18p": "", "19c": "", "19p": "", "20c": "14", "20p": "11", "21c": "", "21p": "", "22c": "", "22p": "", "23c": "", "23p": "", "24c": "", "24p": "", "total": "14"}, 
  {"pos": "56", "name": "Huey Duck", "world": "Fissure of Woe", "1c": "", "1p": "", "2c": "", "2p": "", "3c": "", "3p": "", "4c": "", "4p": "", "5c": "", "5p": "", "6c": "", "6p": "", "7c": "", "7p": "", "8c": "", "8p": "", "9c": "", "9p": "", "10c": "", "10p": "", "11c": "", "11p": "", "12c": "", "12p": "", "13c": "", "13p": "", "14c": "", "14p": "", "15c": "", "15p": "", "16c": "", "16p": "", "17c": "", "17p": "", "18c": "", "18p": "", "19c": "", "19p": "", "20c": "9", "20p": "13", "21c": "", "21p": "", "22c": "", "22p": "", "23c": "", "23p": "", "24c": "", "24p": "", "total": "9"}, 
  {"pos": "57", "name": "Homer Simpson", "world": "Northern Shiverpeaks", "1c": "", "1p": "", "2c": "4", "2p": "18", "3c": "", "3p": "", "4c": "", "4p": "", "5c": "", "5p": "", "6c": "", "6p": "", "7c": "", "7p": "", "8c": "", "8p": "", "9c": "", "9p": "", "10c": "", "10p": "", "11c": "", "11p": "", "12c": "", "12p": "", "13c": "", "13p": "", "14c": "", "14p": "", "15c": "", "15p": "", "16c": "", "16p": "", "17c": "", "17p": "", "18c": "", "18p": "", "19c": "", "19p": "", "20c": "", "20p": "", "21c": "", "21p": "", "22c": "", "22p": "", "23c": "", "23p": "", "24c": "", "24p": "", "total": "4"}
],
"commentary": [
  {"comment": "1st place, with  kills in 2 hours of play is Bob the Dog from Yak's Bend"},
  {"comment": "2nd place, with 25 kills in 2 hours of play is Skritt Forager from Abaddon's Mouth"},
  {"comment": "3rd place, with  kills in 2 hours of play is Batgirl from Ruins of Surmia"},
  {"comment": "Khan from Yak's Bend killed 38 in 30 minutes!"}
]
}
